martinlab/__init__.py
martinlab/camunda/__init__.py
martinlab/camunda/cam.py
martinlab/llmapis/__init__.py
martinlab/llmapis/ratelimiter.py
martinlab_utils-0.1.14.dist-info/LICENSE
martinlab_utils-0.1.14.dist-info/METADATA
martinlab_utils-0.1.14.dist-info/WHEEL
martinlab_utils-0.1.14.dist-info/top_level.txt
martinlab_utils-0.1.14.dist-info/RECORD
